.DS_Store
LICENSE
MANIFEST.in
README.md
setup.py
dist/.DS_Store
xss_svm_detect/.DS_Store
xss_svm_detect/__init__.py
xss_svm_detect/svm-xss-train.pkl
xss_svm_detect.egg-info/PKG-INFO
xss_svm_detect.egg-info/SOURCES.txt
xss_svm_detect.egg-info/dependency_links.txt
xss_svm_detect.egg-info/top_level.txt
xss_svm_detect/DataProcessing/.DS_Store
xss_svm_detect/DataProcessing/.DataProcessor 2.py.icloud
xss_svm_detect/DataProcessing/.MalwareDataProcessor 2.py.icloud
xss_svm_detect/DataProcessing/.NormalDataProcessor 2.py.icloud
xss_svm_detect/DataProcessing/DataProcessor.py
xss_svm_detect/DataProcessing/MalwareDataProcessor.py
xss_svm_detect/DataProcessing/NormalDataProcessor.py
xss_svm_detect/DataProcessing/labeled_data.csv
xss_svm_detect/DataProcessing/readme.txt
xss_svm_detect/DataProcessing/test.py
xss_svm_detect/DataProcessing/xss-20000.txt
xss_svm_detect/DataProcessing/xss-20000url.txt
xss_svm_detect/DataProcessing/xss-train.txt
xss_svm_detect/DataProcessing/.idea/DataProcessing.iml
xss_svm_detect/DataProcessing/.idea/misc.xml
xss_svm_detect/DataProcessing/.idea/modules.xml
xss_svm_detect/DataProcessing/.idea/workspace.xml
xss_svm_detect/DataProcessing/.idea/inspectionProfiles/profiles_settings.xml
xss_svm_detect/DataProcessing/__pycache__/DataProcessor.cpython-37.pyc
xss_svm_detect/DataProcessing/__pycache__/MalwareDataProcessor.cpython-37.pyc
xss_svm_detect/DataProcessing/__pycache__/NormalDataProcessor.cpython-37.pyc
xss_svm_detect/DataProcessing/venv/LICENSE.txt
xss_svm_detect/DataProcessing/venv/Include/Python-ast.h
xss_svm_detect/DataProcessing/venv/Include/Python.h
xss_svm_detect/DataProcessing/venv/Include/abstract.h
xss_svm_detect/DataProcessing/venv/Include/asdl.h
xss_svm_detect/DataProcessing/venv/Include/ast.h
xss_svm_detect/DataProcessing/venv/Include/bitset.h
xss_svm_detect/DataProcessing/venv/Include/boolobject.h
xss_svm_detect/DataProcessing/venv/Include/bufferobject.h
xss_svm_detect/DataProcessing/venv/Include/bytearrayobject.h
xss_svm_detect/DataProcessing/venv/Include/bytes_methods.h
xss_svm_detect/DataProcessing/venv/Include/bytesobject.h
xss_svm_detect/DataProcessing/venv/Include/cStringIO.h
xss_svm_detect/DataProcessing/venv/Lib/site-packages/pip-20.2.3.dist-info/INSTALLER
xss_svm_detect/DataProcessing/venv/Lib/site-packages/pip-20.2.3.dist-info/LICENSE.txt
xss_svm_detect/DataProcessing/venv/Lib/site-packages/pip-20.2.3.dist-info/METADATA
xss_svm_detect/DataProcessing/venv/Lib/site-packages/pip-20.2.3.dist-info/RECORD
xss_svm_detect/DataProcessing/venv/Lib/site-packages/pip-20.2.3.dist-info/WHEEL
xss_svm_detect/DataProcessing/venv/Lib/site-packages/pip-20.2.3.dist-info/entry_points.txt
xss_svm_detect/DataProcessing/venv/Lib/site-packages/pip-20.2.3.dist-info/top_level.txt
xss_svm_detect/DataProcessing/venv/Lib/site-packages/setuptools-44.1.1.dist-info/INSTALLER
xss_svm_detect/DataProcessing/venv/Lib/site-packages/setuptools-44.1.1.dist-info/LICENSE
xss_svm_detect/DataProcessing/venv/Lib/site-packages/setuptools-44.1.1.dist-info/METADATA
xss_svm_detect/DataProcessing/venv/Lib/site-packages/setuptools-44.1.1.dist-info/RECORD
xss_svm_detect/DataProcessing/venv/Lib/site-packages/setuptools-44.1.1.dist-info/WHEEL
xss_svm_detect/DataProcessing/venv/Lib/site-packages/setuptools-44.1.1.dist-info/dependency_links.txt
xss_svm_detect/DataProcessing/venv/Lib/site-packages/setuptools-44.1.1.dist-info/entry_points.txt
xss_svm_detect/DataProcessing/venv/Lib/site-packages/setuptools-44.1.1.dist-info/top_level.txt
xss_svm_detect/DataProcessing/venv/Lib/site-packages/setuptools-44.1.1.dist-info/zip-safe
xss_svm_detect/DataProcessing/venv/Lib/site-packages/wheel-0.35.1.dist-info/INSTALLER
xss_svm_detect/DataProcessing/venv/Lib/site-packages/wheel-0.35.1.dist-info/LICENSE.txt
xss_svm_detect/DataProcessing/venv/Lib/site-packages/wheel-0.35.1.dist-info/METADATA
xss_svm_detect/DataProcessing/venv/Lib/site-packages/wheel-0.35.1.dist-info/RECORD
xss_svm_detect/DataProcessing/venv/Lib/site-packages/wheel-0.35.1.dist-info/WHEEL
xss_svm_detect/DataProcessing/venv/Lib/site-packages/wheel-0.35.1.dist-info/entry_points.txt
xss_svm_detect/DataProcessing/venv/Lib/site-packages/wheel-0.35.1.dist-info/top_level.txt
