Metadata-Version: 2.1
Name: xss-svm-detect
Version: 0.0.9
Summary: A SVM mode for detect xss payload
Home-page: https://github.ccs.neu.edu/Capstone-Team/svm
Author: SJLiu
Author-email: liu.so@northeastern.edu
License: UNKNOWN
Platform: UNKNOWN
Classifier: Programming Language :: Python :: 3
Classifier: License :: OSI Approved :: MIT License
Classifier: Operating System :: OS Independent
